pystratum_cli/__init__.py
pystratum_cli/application/StratumApplication.py
pystratum_cli/application/__init__.py
pystratum_cli/command/BaseCommand.py
pystratum_cli/command/ConstantsCommand.py
pystratum_cli/command/RoutineLoaderCommand.py
pystratum_cli/command/RoutineWrapperCommand.py
pystratum_cli/command/StratumCommand.py
pystratum_cli/command/__init__.py
pystratum_cli-2.1.0.dist-info/LICENSE.md
pystratum_cli-2.1.0.dist-info/METADATA
pystratum_cli-2.1.0.dist-info/WHEEL
pystratum_cli-2.1.0.dist-info/entry_points.txt
pystratum_cli-2.1.0.dist-info/RECORD
